modshim/__init__.py
modshim/py.typed
modshim-0.4.0.dist-info/METADATA
modshim-0.4.0.dist-info/WHEEL
modshim-0.4.0.dist-info/licenses/LICENSE
modshim-0.4.0.dist-info/RECORD
