Metadata-Version: 2.4
Name: modshim
Version: 0.4.0
Summary: Override and customize Python packages without touching their code.
Author-email: Josiah Outram Halstead <josiah@halstead.email>
License-File: LICENSE
Requires-Python: >=3.9
